fritter/__init__.py
fritter/boundaries.py
fritter/heap.py
fritter/py.typed
fritter/scheduler.py
fritter/tree.py
fritter/drivers/__init__.py
fritter/drivers/asyncio.py
fritter/drivers/datetimes.py
fritter/drivers/memory.py
fritter/drivers/sleep.py
fritter/drivers/twisted.py
fritter/persistent/__init__.py
fritter/persistent/jsonable.py
fritter/repeat/__init__.py
fritter/repeat/rules/__init__.py
fritter/repeat/rules/datetimes.py
fritter/repeat/rules/seconds.py
fritter/test/__init__.py
fritter/test/test_asyncio.py
fritter/test/test_datetime.py
fritter/test/test_json.py
fritter/test/test_pq.py
fritter/test/test_repeat.py
fritter/test/test_scheduler.py
fritter/test/test_sleep.py
fritter/test/test_testing.py
fritter/test/test_tree.py
fritter/test/test_twisted.py
fritter-0.1.1.dist-info/licenses/LICENSE
fritter-0.1.1.dist-info/WHEEL
fritter-0.1.1.dist-info/METADATA
fritter-0.1.1.dist-info/RECORD
