Metadata-Version: 2.4
Name: fritter
Version: 0.1.1
Summary: Fritter, the Frame-Rate IndependenT TimEr tRee.
Author-email: Glyph <glyph@glyph.im>
Requires-Python: >=3.9
Classifier: License :: OSI Approved :: MIT License
Classifier: Development Status :: 2 - Pre-Alpha
Classifier: Operating System :: OS Independent
License-File: LICENSE
Requires-Dist: datetype
Requires-Dist: tzdata
Requires-Dist: typing_extensions; python_version < '3.11'
Project-URL: Home, https://github.com/glyph/Fritter
